Metadata-Version: 2.1
Name: dataapipython
Version: 0.0.0rc0
Summary: Pharo Package
Author: pharo-itops
